greenland/hello/.gitignore
greenland/hello/__init__.py
greenland/hello/__version__.py
greenland/hello/version.py
greenland/hello/bin/__init__.py
greenland/hello/bin/greenland_hello.py
greenland_hello-0.1.4.dist-info/METADATA
greenland_hello-0.1.4.dist-info/WHEEL
greenland_hello-0.1.4.dist-info/licenses/LICENSE.txt
greenland_hello-0.1.4.dist-info/RECORD
